MeisterInSitu/Baseline.py
MeisterInSitu/Baseline2.py
MeisterInSitu/Derivative.py
MeisterInSitu/G.py
MeisterInSitu/GRCluster.py
MeisterInSitu/GRCombine.py
MeisterInSitu/GRMain.py
MeisterInSitu/GRPretreat.py
MeisterInSitu/GRPurge.py
MeisterInSitu/GRcb.py
MeisterInSitu/GRfgE.py
MeisterInSitu/GRfnnls.py
MeisterInSitu/GRtb2.py
MeisterInSitu/Smoothing.py
MeisterInSitu/SpEnd.py
MeisterInSitu/WelcomePage.py
MeisterInSitu/__init__.py
MeisterInSitu-2.0.0.dist-info/METADATA
MeisterInSitu-2.0.0.dist-info/WHEEL
MeisterInSitu-2.0.0.dist-info/top_level.txt
MeisterInSitu-2.0.0.dist-info/RECORD
