Metadata-Version: 2.1
Name: MeisterInSitu
Version: 2.0.0
Summary: A Python library to aid in the processing and interpretation of Hyper spectrometric data.
Home-page: https://github.com/JiaqiMEI/InSituAnalyze
Author: Jiaqi Mei, Keke Liao, Zengling Yang
License: MIT
Keywords: Hyper-spectrum,FT-IR spec
Platform: UNKNOWN
Classifier: Programming Language :: Python :: 3
Classifier: License :: OSI Approved :: MIT License
Classifier: Development Status :: 5 - Production/Stable
Classifier: Intended Audience :: Science/Research
Classifier: Topic :: Scientific/Engineering :: Chemistry
Classifier: Topic :: Scientific/Engineering :: Information Analysis
Classifier: Operating System :: OS Independent
Classifier: Natural Language :: English
Requires-Dist: numpy (>=1.14.2)
Requires-Dist: matplotlib (>=2.1.2)
Requires-Dist: scipy (>=1.1.0)
Requires-Dist: scikit-image
Requires-Dist: Opencv-python
Requires-Dist: Pillow
Requires-Dist: scikit-learn
Requires-Dist: wxPython (>=4.0.0)
